nonebot_plugin_llm_plugins_call/__init__.py
nonebot_plugin_llm_plugins_call/config.py
nonebot_plugin_llm_plugins_call-0.2.1.dist-info/METADATA
nonebot_plugin_llm_plugins_call-0.2.1.dist-info/WHEEL
nonebot_plugin_llm_plugins_call-0.2.1.dist-info/RECORD
